[
  {
    "id": "btel_beacon",
    "type": "TOOL",
    "symbol": "#",
    "color": "green",
    "name": "teleporter beacon",
    "description": "A small bundle of sensors, memory storage, and quantum circuitry.  Using it once will capture location data; using it again will allow you to teleport to that location.  Keeping location data maintained will slowly consume electricity, and teleporting will require a LOT!",
    "price": 400000,
    "material": ["plastic", "aluminum"],
    "weight": 150,
    "volume": 3,
    "to_hit": 1,
    "bashing": 5,
    "revert_to": "btel_beacon",
    "use_action": "BTELSTORE",
	"//": "TODO: see about adding a world-global registry for teleporter locations, in order to make them installable on e.g. vehicles"
  }
]
